setup.py
ube/__init__.py
ube.egg-info/PKG-INFO
ube.egg-info/SOURCES.txt
ube.egg-info/dependency_links.txt
ube.egg-info/requires.txt
ube.egg-info/top_level.txt
ube/api/__init__.py
ube/api/tree/__init__.py
ube/api/tree/access.py
ube/api/tree/const.py
ube/api/tree/node.py
ube/api/tree/resources/__init__.py
ube/api/tree/resources/xml/__init__.py
ube/api/tree/tests/__init__.py
ube/api/tree/tests/node_test.py
ube/common/__init__.py
ube/common/authentication.py
ube/common/listhelper.py
ube/common/session.py
ube/common/settings.py
ube/common/users.py
ube/concerns/__init__.py
ube/concerns/aspect_utilities.py
ube/concerns/connection.py
ube/concerns/internal.py
ube/concerns/memoize.py
ube/concerns/permission.py
ube/concerns/security.py
ube/concerns/tests/__init__.py
ube/concerns/tests/connection_check_c.py
ube/concerns/tests/connection_test.py
ube/concerns/tests/internal_test.py
ube/db_upgrader/__init__.py
ube/db_upgrader/db_upgrader.py
ube/db_upgrader/tests/__init__.py
ube/db_upgrader/tests/db_staging_helper.py
ube/db_upgrader/tests/db_upgrader_test.py
ube/db_upgrader/tests/resources/__init__.py
ube/db_upgrader/tests/resources/postgres/__init__.py
ube/db_upgrader/xml/__init__.py