Metadata-Version: 1.0
Name: ube
Version: 0.1
Summary: Unified Back End(UBE) is a collection of libraries used by the UnifiedBPM system.
Home-page: http://sourceforge.net/projects/ube/
Author: Nicklas Boerjesson
Author-email: nicklasb_attheold_gmaildotcom
License: BSD
Platform: UNKNOWN
